academia_mcp/__init__.py
academia_mcp/__main__.py
academia_mcp/files.py
academia_mcp/llm.py
academia_mcp/pdf.py
academia_mcp/py.typed
academia_mcp/server.py
academia_mcp/settings.py
academia_mcp/utils.py
academia_mcp/auth/__init__.py
academia_mcp/auth/cli.py
academia_mcp/auth/middleware.py
academia_mcp/auth/models.py
academia_mcp/auth/token_manager.py
academia_mcp/latex_templates/agents4science_2025/agents4science_2025.sty
academia_mcp/latex_templates/agents4science_2025/agents4science_2025.tex
academia_mcp/tools/__init__.py
academia_mcp/tools/anthology_search.py
academia_mcp/tools/arxiv_download.py
academia_mcp/tools/arxiv_search.py
academia_mcp/tools/bitflip.py
academia_mcp/tools/document_qa.py
academia_mcp/tools/hf_datasets_search.py
academia_mcp/tools/image_processing.py
academia_mcp/tools/latex.py
academia_mcp/tools/py.typed
academia_mcp/tools/review.py
academia_mcp/tools/s2.py
academia_mcp/tools/speech_to_text.py
academia_mcp/tools/visit_webpage.py
academia_mcp/tools/web_search.py
academia_mcp/tools/yt_transcript.py
academia_mcp-1.13.4.dist-info/licenses/LICENSE
academia_mcp-1.13.4.dist-info/METADATA
academia_mcp-1.13.4.dist-info/WHEEL
academia_mcp-1.13.4.dist-info/entry_points.txt
academia_mcp-1.13.4.dist-info/top_level.txt
academia_mcp-1.13.4.dist-info/RECORD
