Metadata-Version: 2.4
Name: academia-mcp
Version: 1.13.4
Summary: MCP server that provides different tools to search for scientific publications
Author-email: Ilya Gusev <phoenixilya@gmail.com>
Project-URL: Homepage, https://github.com/IlyaGusev/academia_mcp
Classifier: Programming Language :: Python :: 3
Classifier: License :: OSI Approved :: MIT License
Classifier: Operating System :: OS Independent
Requires-Python: <=3.13,>=3.12
License-File: LICENSE
Requires-Dist: mcp>=1.10.1
Requires-Dist: xmltodict>=0.14.0
Requires-Dist: requests>=2.32.0
Requires-Dist: pypdf>=5.1.0
Requires-Dist: beautifulsoup4>=4.12.0
Requires-Dist: markdownify==0.14.1
Requires-Dist: types-xmltodict>=0.14.0
Requires-Dist: types-requests>=2.32.0
Requires-Dist: types-beautifulsoup4>=4.12.0
Requires-Dist: acl-anthology==0.5.2
Requires-Dist: huggingface-hub>=0.32.4
Requires-Dist: fire>=0.7.0
Requires-Dist: openai>=1.97.1
Requires-Dist: jinja2>=3.1.6
Requires-Dist: datasets>=4.0.0
Requires-Dist: pymupdf>=1.26.4
Requires-Dist: pillow>=11.3.0
Requires-Dist: pydantic-settings>=2.6.0
Requires-Dist: rich>=13.0.0
Requires-Dist: youtube-transcript-api>=1.2.2
Requires-Dist: paddlepaddle==3.2.0
Requires-Dist: paddleocr==3.2.0
Dynamic: license-file
